sset/__init__.py
sset/christina_example.py
sset/discarded_code.py
sset/ellc_documentation.txt
sset/field.py
sset/fit_bkg_debugged.py
sset/generator_classes.py
sset/generator_classes10.py
sset/goddard_work.ipynb
sset/kepler_cbv.ipynb
sset/put_it_together.ipynb
sset/tess_cbv.ipynb
sset/trc_funcs.py
sset-0.1.0.dist-info/LICENSE
sset-0.1.0.dist-info/WHEEL
sset-0.1.0.dist-info/METADATA
sset-0.1.0.dist-info/RECORD
