Metadata-Version: 2.1
Name: sset
Version: 0.1.0
Summary: A tool for generating simulated cut outs of TESS target pixel files.
License: MIT
Author: rae-holcomb
Author-email: raeholcomb15@gmail.com
Requires-Python: >=3.8,<4.0
Classifier: License :: OSI Approved :: MIT License
Classifier: Programming Language :: Python :: 3
Classifier: Programming Language :: Python :: 3.8
Classifier: Programming Language :: Python :: 3.9
Classifier: Programming Language :: Python :: 3.10
Classifier: Programming Language :: Python :: 3.11
Requires-Dist: ellc (>=1.8.8,<2.0.0)
Requires-Dist: lightkurve (>=2.3.0,<3.0.0)
Requires-Dist: numpy (>1.20.1)
Requires-Dist: pytest (>=7.2.1,<8.0.0)
Requires-Dist: tess-prf (>=0.1.3,<0.2.0)
